tex_lib/__init__.py
tex_lib/generate_pdf.py
tex_lib/generator.py
tex_lib/make_table.py
tex_lib/make_table_and_image.py
my_tex_lib-0.1.2.dist-info/METADATA
my_tex_lib-0.1.2.dist-info/WHEEL
my_tex_lib-0.1.2.dist-info/top_level.txt
my_tex_lib-0.1.2.dist-info/RECORD
